Metadata-Version: 2.1
Name: vectara-cli
Version: 0.2.0
Summary: A CLI tool for interacting with the Vectara platform, including advanced text processing and indexing features.
Home-page: https://git.tonic-ai.com/releases/vectara-cli
Author: Tonic-AI
Author-email: team@tonic-ai.com
License: MIT
Keywords: vectara search-engine document-indexing text-analysis information-retrieval natural-language-processing cli-tool data-science machine-learning text-processing
Classifier: Programming Language :: Python :: 3
Classifier: License :: OSI Approved :: MIT License
Classifier: Operating System :: OS Independent
Classifier: Intended Audience :: Developers
Classifier: Topic :: Software Development :: Libraries :: Python Modules
Classifier: Topic :: Utilities
Requires-Python: >=3.9
License-File: LICENSE.md
Requires-Dist: requests
Requires-Dist: argparse
Provides-Extra: rebel_span
Requires-Dist: accelerate ; extra == 'rebel_span'
Requires-Dist: torch >=1.8.0 ; extra == 'rebel_span'
Requires-Dist: transformers >=4.5.0 ; extra == 'rebel_span'
Requires-Dist: span-marker ; extra == 'rebel_span'
Requires-Dist: spacy ; extra == 'rebel_span'
